sqlquery/__init__.py
sqlquery/dialects.py
sqlquery/lib.py
sqlquery/sql.py
sql_query-0.4.1.dist-info/LICENSE
sql_query-0.4.1.dist-info/METADATA
sql_query-0.4.1.dist-info/WHEEL
sql_query-0.4.1.dist-info/top_level.txt
sql_query-0.4.1.dist-info/RECORD
