Metadata-Version: 2.1
Name: sql-query
Version: 0.4.1
Summary: Write queries in SQL.
Home-page: https://github.com/blackearth/sql-query
Author: Sean Harrison
Author-email: sah@bookgenesis.com
License: MPL 2.0
Platform: UNKNOWN
Classifier: Development Status :: 3 - Alpha
Classifier: Intended Audience :: Developers
Classifier: License :: OSI Approved :: Mozilla Public License 2.0 (MPL 2.0)
Classifier: Programming Language :: Python :: 3
Provides-Extra: test
Provides-Extra: dev
